{
  "review_id": "f9d3c442-515a-4ab4-b17e-6271cb456ddd",
  "star": 1,
  "is_update": false,
  "user_time": 1778814454,
  "dev_time": 0,
  "text_original": "only men bots",
  "text_zh": "仅限男性机器人",
  "reply_original": "Hi there! I'm sorry for the misunderstanding. Actually, we have a huge variety of female characters too! You can find them by exploring the homepage or using the \"Filter\" function to browse different categories.\n\nIf you're having trouble finding them or have specific suggestions, please email us at support@fantachat.ai.",
  "reply_zh": "你好！很抱歉造成了误解。实际上，我们也有非常丰富的女性角色！你可以通过浏览首页或使用“筛选”功能来查看不同的类别。\n\n如果你在查找过程中遇到困难，或者有具体的建议，请发送邮件至 support@fantachat.ai 联系我们。",
  "created_at": 1778825114
}