{
  "review_id": "772608a8-4d26-481c-ac96-e1eadf6932cf",
  "star": 5,
  "is_update": false,
  "user_time": 1779485805,
  "dev_time": 0,
  "text_original": "Divertido!",
  "text_zh": "太有趣了！",
  "reply_original": "¡Qué alegría que te estés divirtiendo en Fantasia! Nos encanta saber que disfrutas la experiencia con nuestros personajes. Trabajamos cada día para que tus historias sean cada vez más mágicas y entretenidas. Si alguna vez tienes sugerencias o necesitas ayuda, escríbenos a support@fantachat.ai. ¡Gracias por tu apoyo y sigue disfrutando!",
  "reply_zh": "很高兴你在 Fantasia 玩得开心！我们很高兴看到你喜欢与我们角色的互动体验。我们每天都在努力，让你的故事变得越来越神奇且有趣。如果你有任何建议或需要帮助，请随时联系我们：support@fantachat.ai。感谢你的支持，请继续享受其中吧！",
  "created_at": 1779671499,
  "published_at": 1779671501,
  "auto_published": true
}