{
  "review_id": "d4e600cf-b8ce-4ced-9f21-35270eb9149e",
  "star": 5,
  "is_update": false,
  "user_time": 1780786580,
  "dev_time": 0,
  "text_original": "muito muito bom",
  "text_zh": "非常好",
  "reply_original": "Obrigado pela sua avaliação! Sua adoração nos motiva a continuar criando experiências únicas. Se precisar de ajuda, não hesite em nos contatar: support@fantachat.ai. Que tenha um ótimo dia!",
  "reply_zh": "感谢您的评价！您的喜爱激励我们继续创造独特体验。如需帮助，请随时联系我们：support@fantachat.ai。祝您一天愉快！",
  "created_at": 1780883682,
  "published_at": 1780883683,
  "auto_published": true
}